[
  {
    "accountName": "OfficeClip LLC",
    "accountSid": "4A9RY7EVHA8CNSHRJBLNB3HRD6TLYUEXYCYM6LQ",
    "breakTime": "",
    "checkInTime": "2021-02-19 17:00:00Z",
    "checkOutTime": "2021-02-19 18:00:00Z",
    "createdDate": "2020-11-03 11:48:27Z",
    "createdUserSid": "D48MY4GRRCKLNUW34ARZYESEDM4VNBSFM89M6LQ",
    "description": "1.1.4.1.50.12.14 New Timesheet 3",
    "isBillable": true,
    "modifiedDate": "2020-11-03 11:48:27Z",
    "modifiedUserSid": "D48MY4GRRCKLNUW34ARZYESEDM4VNBSFM89M6LQ",
    "payrollName": "",
    "payrollSid": "ECHTWHSFBJ9CW39XAC5Q",
    "projectName": "",
    "projectSid": "5JRMY8SR7JYVSHDRJC5Q",
    "serviceItemName": "Development",
    "serviceItemSid": "VMTV6WGXN6HE2CD4HDGWXFJER86E369S5DYM6LQ",
    "taskDate": "2020-11-02 18:30:00Z",
    "timeDuration": 1.0,
    "timesheetDetailSid": "N48KW7A5FZFV77KFSZNUXZS3U6NXY2GC2CTM6LQ",
    "timesheetSid": "D4KEN6S4HAGZXJTXSMBYSRDR548MNNAXN8JM6LQ"
  },
  {
    "accountName": "OfficeClip LLC",
    "accountSid": "4A9RY7EVHA8CNSHRJBLNB3HRD6TLYUEXYCYM6LQ",
    "breakTime": "",
    "checkInTime": "2021-02-19 19:00:00Z",
    "checkOutTime": "2021-02-19 22:00:00Z",
    "createdDate": "2020-11-03 11:48:27Z",
    "createdUserSid": "D48MY4GRRCKLNUW34ARZYESEDM4VNBSFM89M6LQ",
    "description": "Reviewed screens and reported issues in google drive.\nReview Contact ADMIN still pending",
    "isBillable": true,
    "modifiedDate": "2020-11-03 11:48:27Z",
    "modifiedUserSid": "D48MY4GRRCKLNUW34ARZYESEDM4VNBSFM89M6LQ",
    "payrollName": "",
    "payrollSid": "ECHTWHSFBJ9CW39XAC5Q",
    "projectName": "",
    "projectSid": "5JRMY8SR7JYVSHDRJC5Q",
    "serviceItemName": "Testing",
    "serviceItemSid": "B6RC7MS4MCTYH7EV7ZFRSURDNCVZY3JE6M9M6LQ",
    "taskDate": "2020-11-02 18:30:00Z",
    "timeDuration": 3.0,
    "timesheetDetailSid": "N48KW7A5FZFV77KF3CNRY2HXB26KX2S5789M6LQ",
    "timesheetSid": "D4KEN6S4HAGZXJTXSMBYSRDR548MNNAXN8JM6LQ"
  },
  {
    "accountName": "OfficeClip LLC",
    "accountSid": "4A9RY7EVHA8CNSHRJBLNB3HRD6TLYUEXYCYM6LQ",
    "breakTime": ".5",
    "checkInTime": "2021-02-19 16:00:00Z",
    "checkOutTime": "2021-02-19 19:30:00Z",
    "createdDate": "2020-11-04 15:03:49Z",
    "createdUserSid": "D48MY4GRRCKLNUW34ARZYESEDM4VNBSFM89M6LQ",
    "description": "1.1.4.1.56.1 CRM Module",
    "isBillable": true,
    "modifiedDate": "2020-11-04 15:03:49Z",
    "modifiedUserSid": "D48MY4GRRCKLNUW34ARZYESEDM4VNBSFM89M6LQ",
    "payrollName": "",
    "payrollSid": "ECHTWHSFBJ9CW39XAC5Q",
    "projectName": "",
    "projectSid": "5JRMY8SR7JYVSHDRJC5Q",
    "serviceItemName": "Testing",
    "serviceItemSid": "B6RC7MS4MCTYH7EV7ZFRSURDNCVZY3JE6M9M6LQ",
    "taskDate": "2020-11-03 18:30:00Z",
    "timeDuration": 3.0,
    "timesheetDetailSid": "N48KW7A5FZFV77KF3C8VWHFVXZVZS3ADYDTM6LQ",
    "timesheetSid": "D4KEN6S4HAGZXJTXSMBYSRDR548MNNAXN8JM6LQ"
  },
  {
    "accountName": "OfficeClip LLC",
    "accountSid": "4A9RY7EVHA8CNSHRJBLNB3HRD6TLYUEXYCYM6LQ",
    "breakTime": "",
    "checkInTime": "2021-02-19 20:00:00Z",
    "checkOutTime": "2021-02-19 22:00:00Z",
    "createdDate": "2020-11-04 15:03:49Z",
    "createdUserSid": "D48MY4GRRCKLNUW34ARZYESEDM4VNBSFM89M6LQ",
    "description": "Facing issue with the new release.\nDiscussed with the team and finalized to fix the issue and make a new release 10.9.9",
    "isBillable": true,
    "modifiedDate": "2020-11-04 15:03:49Z",
    "modifiedUserSid": "D48MY4GRRCKLNUW34ARZYESEDM4VNBSFM89M6LQ",
    "payrollName": "",
    "payrollSid": "ECHTWHSFBJ9CW39XAC5Q",
    "projectName": "",
    "projectSid": "5JRMY8SR7JYVSHDRJC5Q",
    "serviceItemName": "Testing",
    "serviceItemSid": "B6RC7MS4MCTYH7EV7ZFRSURDNCVZY3JE6M9M6LQ",
    "taskDate": "2020-11-03 18:30:00Z",
    "timeDuration": 2.0,
    "timesheetDetailSid": "N48KW7A5FZFV77KFEZRX7KRF248LB6D56DYM6LQ",
    "timesheetSid": "D4KEN6S4HAGZXJTXSMBYSRDR548MNNAXN8JM6LQ"
  },
  {
    "accountName": "OfficeClip LLC",
    "accountSid": "4A9RY7EVHA8CNSHRJBLNB3HRD6TLYUEXYCYM6LQ",
    "breakTime": "",
    "checkInTime": "2021-02-20 00:30:00Z",
    "checkOutTime": "2021-02-20 01:30:00Z",
    "createdDate": "2020-11-04 05:46:05Z",
    "createdUserSid": "D48MY4GRRCKLNUW34ARZYESEDM4VNBSFM89M6LQ",
    "description": "Meeting with team regarding the status that is done and that needs to be done.",
    "isBillable": true,
    "modifiedDate": "2020-11-04 05:46:05Z",
    "modifiedUserSid": "D48MY4GRRCKLNUW34ARZYESEDM4VNBSFM89M6LQ",
    "payrollName": "",
    "payrollSid": "ECHTWHSFBJ9CW39XAC5Q",
    "projectName": "",
    "projectSid": "5JRMY8SR7JYVSHDRJC5Q",
    "serviceItemName": "Meetings",
    "serviceItemSid": "B6RC7MS4MCTYH7EV7MRENSSR26TBN4AC58JM6LQ",
    "taskDate": "2020-11-02 18:30:00Z",
    "timeDuration": 1.0,
    "timesheetDetailSid": "N48KW7A5FZFV77KF3BBWSWJFBGMENUTEXCTM6LQ",
    "timesheetSid": "D4KEN6S4HAGZXJTXSMBYSRDR548MNNAXN8JM6LQ"
  },
  {
    "accountName": "OfficeClip LLC",
    "accountSid": "4A9RY7EVHA8CNSHRJBLNB3HRD6TLYUEXYCYM6LQ",
    "breakTime": "",
    "checkInTime": "2021-02-20 01:00:00Z",
    "checkOutTime": "2021-02-20 02:15:00Z",
    "createdDate": "2020-11-04 15:43:52Z",
    "createdUserSid": "D48MY4GRRCKLNUW34ARZYESEDM4VNBSFM89M6LQ",
    "description": "Meeting with team regarding status that is done and that needs to be done.",
    "isBillable": true,
    "modifiedDate": "2020-11-04 15:43:52Z",
    "modifiedUserSid": "D48MY4GRRCKLNUW34ARZYESEDM4VNBSFM89M6LQ",
    "payrollName": "",
    "payrollSid": "ECHTWHSFBJ9CW39XAC5Q",
    "projectName": "",
    "projectSid": "5JRMY8SR7JYVSHDRJC5Q",
    "serviceItemName": "Meetings",
    "serviceItemSid": "B6RC7MS4MCTYH7EV7MRENSSR26TBN4AC58JM6LQ",
    "taskDate": "2020-11-03 18:30:00Z",
    "timeDuration": 1.25,
    "timesheetDetailSid": "N48KW7A5FZFV77KFSMHEH8EXBCHWWEJVFCYM6LQ",
    "timesheetSid": "D4KEN6S4HAGZXJTXSMBYSRDR548MNNAXN8JM6LQ"
  },
  {
    "accountName": "OfficeClip LLC",
    "accountSid": "4A9RY7EVHA8CNSHRJBLNB3HRD6TLYUEXYCYM6LQ",
    "breakTime": "",
    "checkInTime": "2021-02-19 12:00:00Z",
    "checkOutTime": "2021-02-19 13:00:00Z",
    "createdDate": "2020-11-03 02:44:42Z",
    "createdUserSid": "D48MY4GRRCKLNUW34ARZYESEDM4VNBSFM89M6LQ",
    "description": "Meeting with Dutta and Sudhakar regarding the work that needs to be done.",
    "isBillable": true,
    "modifiedDate": "2020-11-03 09:22:39Z",
    "modifiedUserSid": "D48MY4GRRCKLNUW34ARZYESEDM4VNBSFM89M6LQ",
    "payrollName": "",
    "payrollSid": "ECHTWHSFBJ9CW39XAC5Q",
    "projectName": "",
    "projectSid": "5JRMY8SR7JYVSHDRJC5Q",
    "serviceItemName": "Meetings",
    "serviceItemSid": "B6RC7MS4MCTYH7EV7MRENSSR26TBN4AC58JM6LQ",
    "taskDate": "2020-11-02 18:30:00Z",
    "timeDuration": 1.0,
    "timesheetDetailSid": "N48KW7A5FZFV77KFSZNYXMYEGC6V7EGEW89M6LQ",
    "timesheetSid": "D4KEN6S4HAGZXJTXSMBYSRDR548MNNAXN8JM6LQ"
  },
  {
    "accountName": "OfficeClip LLC",
    "accountSid": "4A9RY7EVHA8CNSHRJBLNB3HRD6TLYUEXYCYM6LQ",
    "breakTime": "",
    "checkInTime": "2021-02-19 22:30:00Z",
    "checkOutTime": "2021-02-20 01:00:00Z",
    "createdDate": "2020-11-04 15:09:26Z",
    "createdUserSid": "D48MY4GRRCKLNUW34ARZYESEDM4VNBSFM89M6LQ",
    "description": "Tried to install new version but still facing couple of issues. \nAsked help for Narsimha. In mean time tried to to create a new database and install on it. It is working fine.\nNarsimha figured the issue and suggested to revert the version but still facing issue of null value exception.\nHe will get back to me with the fix,",
    "isBillable": true,
    "modifiedDate": "2020-11-04 15:09:26Z",
    "modifiedUserSid": "D48MY4GRRCKLNUW34ARZYESEDM4VNBSFM89M6LQ",
    "payrollName": "",
    "payrollSid": "ECHTWHSFBJ9CW39XAC5Q",
    "projectName": "",
    "projectSid": "5JRMY8SR7JYVSHDRJC5Q",
    "serviceItemName": "Testing",
    "serviceItemSid": "B6RC7MS4MCTYH7EV7ZFRSURDNCVZY3JE6M9M6LQ",
    "taskDate": "2020-11-03 18:30:00Z",
    "timeDuration": 2.5,
    "timesheetDetailSid": "N48KW7A5FZFV77KFEBFWH4SCC8YRN8Q574TM6LQ",
    "timesheetSid": "D4KEN6S4HAGZXJTXSMBYSRDR548MNNAXN8JM6LQ"
  }
]
